tests/__init__.py
tests/test_placeholder.py
vspy/__init__.py
vspy/info.py
vspy/main.py
vspy/project.py
vspy/py.typed
vspy/resource_manager.py
vspy/resources/.editorconfig
vspy/resources/.flake8
vspy/resources/.gitattribute
vspy/resources/.gitignore
vspy/resources/.pre-commit-config.yaml
vspy/resources/CHANGELOG.md
vspy/resources/LICENSE
vspy/resources/main.py
vspy/resources/pyproject.toml
vspy/resources/settings.json
vspy/resources/test.yml
vspy-0.0.1.dist-info/LICENSE
vspy-0.0.1.dist-info/METADATA
vspy-0.0.1.dist-info/WHEEL
vspy-0.0.1.dist-info/entry_points.txt
vspy-0.0.1.dist-info/top_level.txt
vspy-0.0.1.dist-info/RECORD
